formula_thoughts_web/__init__.py
formula_thoughts_web/abstractions.py
formula_thoughts_web/application.py
formula_thoughts_web/crosscutting.py
formula_thoughts_web/events.py
formula_thoughts_web/exceptions.py
formula_thoughts_web/ioc.py
formula_thoughts_web/web.py
formula_thoughts_web-1.3.4.dist-info/METADATA
formula_thoughts_web-1.3.4.dist-info/WHEEL
formula_thoughts_web-1.3.4.dist-info/top_level.txt
formula_thoughts_web-1.3.4.dist-info/RECORD
