Metadata-Version: 2.1
Name: formula-thoughts-web
Version: 1.3.4
Summary: A web library for AWS lambda, gateway and SQS event handling
Author: GanTheMan
Author-email: aidanwilliamgannon@gmail.com
Keywords: python,lambda,api gateway,sqs
Classifier: Development Status :: 1 - Planning
Classifier: Intended Audience :: Developers
Classifier: Programming Language :: Python :: 3
Classifier: Operating System :: Unix
Requires-Dist: jsonschema ==4.21.1
Requires-Dist: filetype ==1.2.0
Requires-Dist: boto3 ==1.34.50
Requires-Dist: validators ==0.22.0
Requires-Dist: punq ==0.7.0
